Gitbigcommits-1.0.3.dist-info/DESCRIPTION.rst
Gitbigcommits-1.0.3.dist-info/METADATA
Gitbigcommits-1.0.3.dist-info/RECORD
Gitbigcommits-1.0.3.dist-info/WHEEL
Gitbigcommits-1.0.3.dist-info/entry_points.txt
Gitbigcommits-1.0.3.dist-info/metadata.json
Gitbigcommits-1.0.3.dist-info/top_level.txt
gitbigcommits/__init__.py
gitbigcommits/core/__init__.py
gitbigcommits/core/git_commit_utility.py
gitbigcommits/core/git_data_collection.py
gitbigcommits/miscellaneous/__init__.py
gitbigcommits/miscellaneous/dorm_branch_info.html
gitbigcommits/miscellaneous/fat_file_user_info.html
gitbigcommits/miscellaneous/gitfat.css
gitbigcommits/prevent_commits/__init__.py
gitbigcommits/prevent_commits/main.py
gitbigcommits/prevent_commits/pre-commit
gitbigcommits/report_layer/__init__.py
gitbigcommits/report_layer/git_html_report.py
