Metadata-Version: 2.0
Name: Gitbigcommits
Version: 1.0.3
Summary: Reporting tool for large commits happened in your git repo
Home-page: UNKNOWN
Author: Viswesh M
Author-email: mviswesh5@gmail.com
License: GNU
Platform: UNKNOWN
Requires-Dist: Cheetah3 (>=3.0.0)
